sheikhfaizancalculator/__init__.py
sheikhfaizancalculator-0.0.1.dist-info/LICENSE.txt
sheikhfaizancalculator-0.0.1.dist-info/METADATA
sheikhfaizancalculator-0.0.1.dist-info/WHEEL
sheikhfaizancalculator-0.0.1.dist-info/top_level.txt
sheikhfaizancalculator-0.0.1.dist-info/RECORD
