Metadata-Version: 2.1
Name: sheikhfaizancalculator
Version: 0.0.1
Summary: Basic Multiplication Package For Python
Home-page: UNKNOWN
Author: Sheikh Faizan
Author-email: 786fzsheikh@gmail.com
License: UNKNOWN
Platform: UNKNOWN
Classifier: Programming Language :: Python :: 3
Classifier: License :: OSI Approved :: MIT License
Classifier: Operating System :: OS Independent
License-File: LICENSE.txt
